<?xml version="1.0" encoding="utf-8"?>
<Document>
  <Engineering version="V19" />
  <SW.Tags.PlcTagTable ID="0">
    <AttributeList>
      <Name>U2Em1_Output</Name>
    </AttributeList>
    <ObjectList>
      <SW.Tags.PlcTag ID="1" CompositionName="Tags">
        <AttributeList>
          <DataTypeName>Bool</DataTypeName>
          <LogicalAddress>%Q30042.0</LogicalAddress>
          <Name>requestTrayDelivery_standalone_U2EM1</Name>
        </AttributeList>
        <ObjectList>
          <MultilingualText ID="2" CompositionName="Comment">
            <ObjectList>
              <MultilingualTextItem ID="3" CompositionName="Items">
                <AttributeList>
                  <Culture>en-US</Culture>
                  <Text />
                </AttributeList>
              </MultilingualTextItem>
              <MultilingualTextItem ID="4" CompositionName="Items">
                <AttributeList>
                  <Culture>fr-FR</Culture>
                  <Text />
                </AttributeList>
              </MultilingualTextItem>
              <MultilingualTextItem ID="5" CompositionName="Items">
                <AttributeList>
                  <Culture>zh-CN</Culture>
                  <Text>单机请求出</Text>
                </AttributeList>
              </MultilingualTextItem>
              <MultilingualTextItem ID="6" CompositionName="Items">
                <AttributeList>
                  <Culture>de-DE</Culture>
                  <Text />
                </AttributeList>
              </MultilingualTextItem>
            </ObjectList>
          </MultilingualText>
        </ObjectList>
      </SW.Tags.PlcTag>
      <SW.Tags.PlcTag ID="7" CompositionName="Tags">
        <AttributeList>
          <DataTypeName>Bool</DataTypeName>
          <LogicalAddress>%Q30042.1</LogicalAddress>
          <Name>vfdBusy_standalone_U2EM1</Name>
        </AttributeList>
        <ObjectList>
          <MultilingualText ID="8" CompositionName="Comment">
            <ObjectList>
              <MultilingualTextItem ID="9" CompositionName="Items">
                <AttributeList>
                  <Culture>en-US</Culture>
                  <Text />
                </AttributeList>
              </MultilingualTextItem>
              <MultilingualTextItem ID="A" CompositionName="Items">
                <AttributeList>
                  <Culture>fr-FR</Culture>
                  <Text />
                </AttributeList>
              </MultilingualTextItem>
              <MultilingualTextItem ID="B" CompositionName="Items">
                <AttributeList>
                  <Culture>zh-CN</Culture>
                  <Text>单机出料中</Text>
                </AttributeList>
              </MultilingualTextItem>
              <MultilingualTextItem ID="C" CompositionName="Items">
                <AttributeList>
                  <Culture>de-DE</Culture>
                  <Text />
                </AttributeList>
              </MultilingualTextItem>
            </ObjectList>
          </MultilingualText>
        </ObjectList>
      </SW.Tags.PlcTag>
      <SW.Tags.PlcTag ID="D" CompositionName="Tags">
        <AttributeList>
          <DataTypeName>Bool</DataTypeName>
          <LogicalAddress>%Q30042.2</LogicalAddress>
          <Name>Received_the_shipment_in_place_U2EM1</Name>
        </AttributeList>
        <ObjectList>
          <MultilingualText ID="E" CompositionName="Comment">
            <ObjectList>
              <MultilingualTextItem ID="F" CompositionName="Items">
                <AttributeList>
                  <Culture>en-US</Culture>
                  <Text />
                </AttributeList>
              </MultilingualTextItem>
              <MultilingualTextItem ID="10" CompositionName="Items">
                <AttributeList>
                  <Culture>fr-FR</Culture>
                  <Text />
                </AttributeList>
              </MultilingualTextItem>
              <MultilingualTextItem ID="11" CompositionName="Items">
                <AttributeList>
                  <Culture>zh-CN</Culture>
                  <Text>单机收到物料</Text>
                </AttributeList>
              </MultilingualTextItem>
              <MultilingualTextItem ID="12" CompositionName="Items">
                <AttributeList>
                  <Culture>de-DE</Culture>
                  <Text />
                </AttributeList>
              </MultilingualTextItem>
            </ObjectList>
          </MultilingualText>
        </ObjectList>
      </SW.Tags.PlcTag>
      <SW.Tags.PlcTag ID="13" CompositionName="Tags">
        <AttributeList>
          <DataTypeName>Bool</DataTypeName>
          <LogicalAddress>%Q30042.3</LogicalAddress>
          <Name>emAlarm_standalone_U2EM1</Name>
        </AttributeList>
        <ObjectList>
          <MultilingualText ID="14" CompositionName="Comment">
            <ObjectList>
              <MultilingualTextItem ID="15" CompositionName="Items">
                <AttributeList>
                  <Culture>en-US</Culture>
                  <Text />
                </AttributeList>
              </MultilingualTextItem>
              <MultilingualTextItem ID="16" CompositionName="Items">
                <AttributeList>
                  <Culture>fr-FR</Culture>
                  <Text />
                </AttributeList>
              </MultilingualTextItem>
              <MultilingualTextItem ID="17" CompositionName="Items">
                <AttributeList>
                  <Culture>zh-CN</Culture>
                  <Text>单机异常</Text>
                </AttributeList>
              </MultilingualTextItem>
              <MultilingualTextItem ID="18" CompositionName="Items">
                <AttributeList>
                  <Culture>de-DE</Culture>
                  <Text />
                </AttributeList>
              </MultilingualTextItem>
            </ObjectList>
          </MultilingualText>
        </ObjectList>
      </SW.Tags.PlcTag>
      <SW.Tags.PlcTag ID="19" CompositionName="Tags">
        <AttributeList>
          <DataTypeName>Bool</DataTypeName>
          <LogicalAddress>%Q30042.4</LogicalAddress>
          <Name>Tray_waiting_to_be_released_U2EM1</Name>
        </AttributeList>
        <ObjectList>
          <MultilingualText ID="1A" CompositionName="Comment">
            <ObjectList>
              <MultilingualTextItem ID="1B" CompositionName="Items">
                <AttributeList>
                  <Culture>en-US</Culture>
                  <Text />
                </AttributeList>
              </MultilingualTextItem>
              <MultilingualTextItem ID="1C" CompositionName="Items">
                <AttributeList>
                  <Culture>fr-FR</Culture>
                  <Text />
                </AttributeList>
              </MultilingualTextItem>
              <MultilingualTextItem ID="1D" CompositionName="Items">
                <AttributeList>
                  <Culture>zh-CN</Culture>
                  <Text>单机有托盘待出</Text>
                </AttributeList>
              </MultilingualTextItem>
              <MultilingualTextItem ID="1E" CompositionName="Items">
                <AttributeList>
                  <Culture>de-DE</Culture>
                  <Text />
                </AttributeList>
              </MultilingualTextItem>
            </ObjectList>
          </MultilingualText>
        </ObjectList>
      </SW.Tags.PlcTag>
      <SW.Tags.PlcTag ID="1F" CompositionName="Tags">
        <AttributeList>
          <DataTypeName>Bool</DataTypeName>
          <LogicalAddress>%Q30043.0</LogicalAddress>
          <Name>Allow_logistics_lines_to_exit_U2EM1</Name>
        </AttributeList>
        <ObjectList>
          <MultilingualText ID="20" CompositionName="Comment">
            <ObjectList>
              <MultilingualTextItem ID="21" CompositionName="Items">
                <AttributeList>
                  <Culture>en-US</Culture>
                  <Text />
                </AttributeList>
              </MultilingualTextItem>
              <MultilingualTextItem ID="22" CompositionName="Items">
                <AttributeList>
                  <Culture>fr-FR</Culture>
                  <Text />
                </AttributeList>
              </MultilingualTextItem>
              <MultilingualTextItem ID="23" CompositionName="Items">
                <AttributeList>
                  <Culture>zh-CN</Culture>
                  <Text>单机允许物流线出</Text>
                </AttributeList>
              </MultilingualTextItem>
              <MultilingualTextItem ID="24" CompositionName="Items">
                <AttributeList>
                  <Culture>de-DE</Culture>
                  <Text />
                </AttributeList>
              </MultilingualTextItem>
            </ObjectList>
          </MultilingualText>
        </ObjectList>
      </SW.Tags.PlcTag>
      <SW.Tags.PlcTag ID="25" CompositionName="Tags">
        <AttributeList>
          <DataTypeName>Bool</DataTypeName>
          <LogicalAddress>%Q30043.1</LogicalAddress>
          <Name>Notify_the_logistics_line_to_arrive_in_place_U2EM1</Name>
        </AttributeList>
        <ObjectList>
          <MultilingualText ID="26" CompositionName="Comment">
            <ObjectList>
              <MultilingualTextItem ID="27" CompositionName="Items">
                <AttributeList>
                  <Culture>en-US</Culture>
                  <Text />
                </AttributeList>
              </MultilingualTextItem>
              <MultilingualTextItem ID="28" CompositionName="Items">
                <AttributeList>
                  <Culture>fr-FR</Culture>
                  <Text />
                </AttributeList>
              </MultilingualTextItem>
              <MultilingualTextItem ID="29" CompositionName="Items">
                <AttributeList>
                  <Culture>zh-CN</Culture>
                  <Text>单机通知物流线出到位</Text>
                </AttributeList>
              </MultilingualTextItem>
              <MultilingualTextItem ID="2A" CompositionName="Items">
                <AttributeList>
                  <Culture>de-DE</Culture>
                  <Text />
                </AttributeList>
              </MultilingualTextItem>
            </ObjectList>
          </MultilingualText>
        </ObjectList>
      </SW.Tags.PlcTag>
      <SW.Tags.PlcTag ID="2B" CompositionName="Tags">
        <AttributeList>
          <DataTypeName>Bool</DataTypeName>
          <LogicalAddress>%Q30043.2</LogicalAddress>
          <Name>Single_machine_output_in_place_signal_U2EM1</Name>
        </AttributeList>
        <ObjectList>
          <MultilingualText ID="2C" CompositionName="Comment">
            <ObjectList>
              <MultilingualTextItem ID="2D" CompositionName="Items">
                <AttributeList>
                  <Culture>en-US</Culture>
                  <Text />
                </AttributeList>
              </MultilingualTextItem>
              <MultilingualTextItem ID="2E" CompositionName="Items">
                <AttributeList>
                  <Culture>fr-FR</Culture>
                  <Text />
                </AttributeList>
              </MultilingualTextItem>
              <MultilingualTextItem ID="2F" CompositionName="Items">
                <AttributeList>
                  <Culture>zh-CN</Culture>
                  <Text>单机收到物流线收到的单机出到位信号</Text>
                </AttributeList>
              </MultilingualTextItem>
              <MultilingualTextItem ID="30" CompositionName="Items">
                <AttributeList>
                  <Culture>de-DE</Culture>
                  <Text />
                </AttributeList>
              </MultilingualTextItem>
            </ObjectList>
          </MultilingualText>
        </ObjectList>
      </SW.Tags.PlcTag>
      <SW.Tags.PlcTag ID="31" CompositionName="Tags">
        <AttributeList>
          <DataTypeName>Bool</DataTypeName>
          <LogicalAddress>%Q30043.3</LogicalAddress>
          <Name>idle_standalone_U2EM1</Name>
        </AttributeList>
        <ObjectList>
          <MultilingualText ID="32" CompositionName="Comment">
            <ObjectList>
              <MultilingualTextItem ID="33" CompositionName="Items">
                <AttributeList>
                  <Culture>en-US</Culture>
                  <Text />
                </AttributeList>
              </MultilingualTextItem>
              <MultilingualTextItem ID="34" CompositionName="Items">
                <AttributeList>
                  <Culture>fr-FR</Culture>
                  <Text />
                </AttributeList>
              </MultilingualTextItem>
              <MultilingualTextItem ID="35" CompositionName="Items">
                <AttributeList>
                  <Culture>zh-CN</Culture>
                  <Text>单机空闲</Text>
                </AttributeList>
              </MultilingualTextItem>
              <MultilingualTextItem ID="36" CompositionName="Items">
                <AttributeList>
                  <Culture>de-DE</Culture>
                  <Text />
                </AttributeList>
              </MultilingualTextItem>
            </ObjectList>
          </MultilingualText>
        </ObjectList>
      </SW.Tags.PlcTag>
    </ObjectList>
  </SW.Tags.PlcTagTable>
</Document>